jk_console/CharacterBuffer.py
jk_console/Console.py
jk_console/ConsoleBuffer.py
jk_console/ConsoleBufferRGB.py
jk_console/ConsoleBufferRGB2.py
jk_console/ConsoleBufferRGB_Mixins.py
jk_console/ConsoleBufferWO.py
jk_console/ConsoleBuffer_Mixins.py
jk_console/ConsoleGraphics.py
jk_console/EventCollector.py
jk_console/FramedBoxSettingsRGB.py
jk_console/IntRGB.py
jk_console/RGBColorMapper.py
jk_console/Rect.py
jk_console/SimpleTable.py
jk_console/_Rect.py
jk_console/__init__.py
jk_console/readchar.py
jk_console/readchar_linux.py
jk_console/readchar_windows.py
jk_console/wrappers.py
jk_console/demo/Effect1.py
jk_console/demo/__init__.py
jk_console/impl/__init__.py
jk_console/impl/_parseCSS.py
jk_console/viewport/Rectangle.py
jk_console/viewport/ViewPort.py
jk_console/viewport/ViewPortBuffer.py
jk_console/viewport/ViewPortBuffer2.py
jk_console/viewport/ViewPortCell.py
jk_console/viewport/ViewPortRGB.py
jk_console/viewport/ViewPortRenderer.py
jk_console/viewport/__init__.py
jk_console-0.2025.2.23.1.dist-info/WHEEL
jk_console-0.2025.2.23.1.dist-info/METADATA
jk_console-0.2025.2.23.1.dist-info/RECORD
