Metadata-Version: 2.1
Name: jk_console
Version: 0.2025.2.23.1
Summary: This python module provides a variety of essential functions for implementing versatile programs using the console. (Please have a look at the documentation for details.)
Keywords: console,terminal,colors,stdin
Author-email: Jürgen Knauth <pubsrc@binary-overflow.de>
Maintainer-email: Jürgen Knauth <pubsrc@binary-overflow.de>
Requires-Python: >=3.8
Classifier: Development Status :: 5 - Production/Stable
Classifier: License :: OSI Approved :: Apache Software License
Classifier: Programming Language :: Python :: 3
Requires-Dist: msvcrt; platform_system=='Windows'
Requires-Dist: jk_terminal_essentials >= 0.2024.2.2
